agitation/__init__.py
agitation/click_utils.py
agitation/config.py
agitation/data_manager.py
agitation/dataset.py
agitation/inference.py
agitation/processing.py
agitation-0.0.2.dist-info/METADATA
agitation-0.0.2.dist-info/WHEEL
agitation-0.0.2.dist-info/entry_points.txt
agitation-0.0.2.dist-info/licenses/LICENSE
agitation-0.0.2.dist-info/RECORD
