Metadata-Version: 2.4
Name: agitation
Version: 0.0.2
Summary: Deep Learning based tool to quantify subject motion in T1w brain MRI
Project-URL: Repository, https://github.com/chbricout/agitation
Author-email: Charles Bricout <bricout.charles@outlook.com>
License-Expression: MIT
License-File: LICENSE
Requires-Python: >=3.11
Requires-Dist: click==8.1.8
Requires-Dist: dotenv==0.9.9
Requires-Dist: monai==1.4.0
Requires-Dist: nibabel==5.3.2
Requires-Dist: pandas==2.2.3
Requires-Dist: platformdirs==4.3.7
Requires-Dist: requests==2.32.3
Requires-Dist: rich==14.0.0
Requires-Dist: torch==2.7.0
Requires-Dist: tqdm==4.67.1
